<materials>

	<material name="Solid">
	
		<passes>
			<pass name="GBuffer">${shaders}/solid.xml:GBuffer</pass>
			<pass name="ShadowPSSM">${shaders}/solid.xml:ShadowPSSM</pass>
			<pass name="ShadowCube">${shaders}/solid.xml:ShadowCube</pass>
		</passes>
		
		<parameters>
			<parameter type="texture">Diffuse</parameter>
			<parameter type="col">Color</parameter>
		</parameters>
		
	</material>
	
	<material name="SolidColor">
	
		<passes>
			<pass name="GBuffer">${shaders}/solid.xml:GBufferColor</pass>
			<pass name="ShadowPSSM">${shaders}/solid.xml:ShadowPSSM</pass>
			<pass name="ShadowCube">${shaders}/solid.xml:ShadowCube</pass>
		</passes>
		
		<parameters>
			<parameter type="col">Color</parameter>
		</parameters>
		
	</material>
	
</materials>